torspy/__init__.py
torspy/cli.py
torspy/scraper/__init__.py
torspy/scraper/analyze.py
torspy/scraper/directories.py
torspy/scraper/download.py
torspy/scraper/html_extract.py
torspy/scraper/links.py
torspy/scraper/scrape.py
torspy/scraper/services.py
torspy/scraper/subdomains.py
torspy/scraper/tor_check.py
torspy-3.0.8.dist-info/LICENSE
torspy-3.0.8.dist-info/METADATA
torspy-3.0.8.dist-info/WHEEL
torspy-3.0.8.dist-info/entry_points.txt
torspy-3.0.8.dist-info/top_level.txt
torspy-3.0.8.dist-info/RECORD
