Metadata-Version: 2.1
Name: torspy
Version: 3.0.8
Summary: torspy is a Python package for exploring .onion sites via Tor. It scrapes HTML content, localizes text, and detects hidden directories. With subdomain scanning, torspy enables thorough reconnaissance.
Home-page: https://github.com/mr-fidal/torspy
Author: Fidal
Author-email: mrfidal@proton.me
Keywords: mrfidal,tor,DarkWeb,onion,torspy,scraping,dark web,web scraping,hidden services,privacy,security,beautifulsoup4,requests,python
Classifier: Programming Language :: Python :: 3
Classifier: License :: OSI Approved :: MIT License
Classifier: Operating System :: OS Independent
Requires-Python: >=3.6
License-File: LICENSE
Requires-Dist: requests
Requires-Dist: beautifulsoup4
